DOMObjects/__init__.py
DOMObjects/flags.py
DOMObjects/leaf.py
DOMObjects/schema.py
DOMObjects-0.1.0b4.dist-info/LICENSE
DOMObjects-0.1.0b4.dist-info/METADATA
DOMObjects-0.1.0b4.dist-info/NOTICE.md
DOMObjects-0.1.0b4.dist-info/WHEEL
DOMObjects-0.1.0b4.dist-info/top_level.txt
DOMObjects-0.1.0b4.dist-info/RECORD
