Metadata-Version: 2.1
Name: DOMObjects
Version: 0.1.0b4
Summary: Create Python DOM style datastructures with ease.
Home-page: https://github.com/villagertech/DOMObjects
Author: Rob MacKinnon
Author-email: rome@villagertech.com
License: MIT
Project-URL: Bug Tracker, https://github.com/villagertech/DOMObjects/issues
Platform: any
Classifier: Programming Language :: Python
Classifier: Development Status :: 4 - Beta
Classifier: Natural Language :: English
Classifier: Environment :: Web Environment
Classifier: Intended Audience :: Developers
Classifier: License :: OSI Approved :: MIT License
Classifier: Operating System :: OS Independent
Requires-Python: >=3.6
License-File: LICENSE
License-File: NOTICE.md
Provides-Extra: testing
Requires-Dist: pytest ; extra == 'testing'
